winzy_create_gif/__init__.py
winzy_create_gif-0.0.1.dist-info/LICENSE
winzy_create_gif-0.0.1.dist-info/METADATA
winzy_create_gif-0.0.1.dist-info/WHEEL
winzy_create_gif-0.0.1.dist-info/entry_points.txt
winzy_create_gif-0.0.1.dist-info/top_level.txt
winzy_create_gif-0.0.1.dist-info/RECORD
