Metadata-Version: 2.1
Name: winzy-create-gif
Version: 0.0.1
Summary: Create gifs from files in a folder.
Author: Sukhbinder Singh
License: Apache-2.0
Project-URL: Homepage, https://github.com/sukhbinder/winzy-create-gif
Project-URL: Changelog, https://github.com/sukhbinder/winzy-create-gif/releases
Project-URL: Issues, https://github.com/sukhbinder/winzy-create-gif/issues
Project-URL: CI, https://github.com/sukhbinder/winzy-create-gif/actions
Classifier: License :: OSI Approved :: Apache Software License
License-File: LICENSE
Requires-Dist: winzy
Requires-Dist: imageio
Provides-Extra: test
Requires-Dist: pytest; extra == "test"
